Metadata-Version: 2.1
Name: odoo13-addon-base_ebill_payment_contract
Version: 13.0.1.0.1
Summary: Base for managing e-billing contracts
Home-page: https://github.com/OCA/edi
Author: Camptocamp,Odoo Community Association (OCA)
Author-email: support@odoo-community.org
License: AGPL-3
Classifier: Programming Language :: Python
Classifier: Framework :: Odoo
Classifier: Framework :: Odoo :: 13.0
Classifier: License :: OSI Approved :: GNU Affero General Public License v3
Requires-Python: >=3.5
Requires-Dist: odoo13-addon-account-invoice-transmit-method
Requires-Dist: odoo <13.1dev,>=13.0a
